flask_form/__init__.py
flask_form-1.0.0.dist-info/LICENSE
flask_form-1.0.0.dist-info/METADATA
flask_form-1.0.0.dist-info/WHEEL
flask_form-1.0.0.dist-info/top_level.txt
flask_form-1.0.0.dist-info/RECORD
