Metadata-Version: 2.1
Name: flask-form
Version: 1.0.0
Summary: A flexible forms validation and rendering library for python
Home-page: https://github.com/jakbin/flask-form
Author: Jak Bin
Author-email: jakbin4747@gmail.com
License: MIT License
Keywords: FLask,flask-form,form
Platform: UNKNOWN
Classifier: Programming Language :: Python :: 3.6
Classifier: License :: OSI Approved :: Apache Software License
Classifier: Natural Language :: English
Classifier: Operating System :: OS Independent
Requires-Python: >=3.6
